julgi/__init__.py
julgi/__main__.py
julgi/__version__.py
julgi/battle.py
julgi/classes.py
julgi/parse.py
julgi/skill/ko.yml
julgi/skill/sort_skill.py
julgi/util.py
julgi_game-0.2.1.dist-info/entry_points.txt
julgi_game-0.2.1.dist-info/WHEEL
julgi_game-0.2.1.dist-info/METADATA
julgi_game-0.2.1.dist-info/licenses/LICENSE
julgi_game-0.2.1.dist-info/RECORD
