Metadata-Version: 2.1
Name: julgi-game
Version: 0.2.1
Summary: 줄기 게임이야!
Keywords: julgi,game,julgi-game
Author-email: Bingsu <ks2515@naver.com>
Requires-Python: >=3.8
Classifier: Programming Language :: Python :: 3.8
Classifier: Topic :: Games/Entertainment
Requires-Dist: kopp>=0.2.1
Requires-Dist: pyyaml
Project-URL: Repository, https://github.com/Bing-su/julgi-game
